mbb_model/mbb.py
mbb_model/mbb_funcs.py
mbb_model-0.0.2.dist-info/LICENSE
mbb_model-0.0.2.dist-info/METADATA
mbb_model-0.0.2.dist-info/WHEEL
mbb_model-0.0.2.dist-info/top_level.txt
mbb_model-0.0.2.dist-info/RECORD
