Metadata-Version: 2.1
Name: mbb_model
Version: 0.0.2
License-File: LICENSE
Requires-Dist: matplotlib
Requires-Dist: astropy
Requires-Dist: numpy
Requires-Dist: scipy
Requires-Dist: emcee
Requires-Dist: re
Requires-Dist: multiprocessing
Requires-Dist: corner
